run_elmer/__init__.py
run_elmer/export.py
run_elmer/run.py
run_elmer/runners/__init__.py
run_elmer/runners/docker.py
tests/__init__.py
tests/test_mesh.py
run_elmer-0.2.0.dist-info/LICENSE
run_elmer-0.2.0.dist-info/METADATA
run_elmer-0.2.0.dist-info/WHEEL
run_elmer-0.2.0.dist-info/top_level.txt
run_elmer-0.2.0.dist-info/RECORD
